thongna-0.2.4.dist-info/METADATA
thongna-0.2.4.dist-info/WHEEL
thongna-0.2.4.dist-info/license_files/LICENSE
thongna/__init__.py
thongna/thongna.cpython-310-aarch64-linux-gnu.so
thongna-0.2.4.dist-info/RECORD
