Metadata-Version: 2.3
Name: thongna
Version: 0.2.4
Classifier: Programming Language :: Rust
Classifier: Programming Language :: Python :: Implementation :: CPython
Classifier: Programming Language :: Python :: Implementation :: PyPy
Classifier: Programming Language :: Python :: 3
Classifier: Programming Language :: Python :: 3.8
Classifier: Programming Language :: Python :: 3.9
Classifier: Programming Language :: Python :: 3.10
Classifier: Programming Language :: Python :: 3.11
Classifier: License :: OSI Approved :: Apache Software License
Classifier: Topic :: Text Processing :: Linguistic
License-File: LICENSE
Summary: Blazing-fast Thai text processing library powered by Rust
Keywords: thai,tokenizer,nlp,word-segmentation
Author: Porameht Khumsombat
Author-email: Porameht Khumsombat <poramehtkh@gmail.com>
License: Apache-2.0
Requires-Python: >=3.8
Project-URL: Repository, https://github.com/porameht/thongna
Project-URL: Bug Tracker, https://github.com/porameht/thongna/issues
